{
	"configurations" : 
	[
		{
			"directories" : 
			[
				{
					"build" : ".",
					"childIndexes" : 
					[
						1,
						2
					],
					"jsonFile" : "directory-.-RelWithDebInfo-d0094a50bb2071803777.json",
					"minimumCMakeVersion" : 
					{
						"string" : "3.17"
					},
					"projectIndex" : 0,
					"source" : ".",
					"targetIndexes" : 
					[
						4
					]
				},
				{
					"build" : "core",
					"jsonFile" : "directory-core-RelWithDebInfo-e3757ce4a321da3133c4.json",
					"minimumCMakeVersion" : 
					{
						"string" : "3.17"
					},
					"parentIndex" : 0,
					"projectIndex" : 0,
					"source" : "core",
					"targetIndexes" : 
					[
						2,
						3
					]
				},
				{
					"build" : "api",
					"jsonFile" : "directory-api-RelWithDebInfo-5ab110d9fc402529b4bb.json",
					"minimumCMakeVersion" : 
					{
						"string" : "3.17"
					},
					"parentIndex" : 0,
					"projectIndex" : 0,
					"source" : "api",
					"targetIndexes" : 
					[
						0,
						1,
						5
					]
				}
			],
			"name" : "RelWithDebInfo",
			"projects" : 
			[
				{
					"directoryIndexes" : 
					[
						0,
						1,
						2
					],
					"name" : "game_motor_engine",
					"targetIndexes" : 
					[
						0,
						1,
						2,
						3,
						4,
						5
					]
				}
			],
			"targets" : 
			[
				{
					"directoryIndex" : 2,
					"id" : "api::@10fae538ba4e8521554e",
					"jsonFile" : "target-api-RelWithDebInfo-7457ed431a14c5c058dc.json",
					"name" : "api",
					"projectIndex" : 0
				},
				{
					"directoryIndex" : 2,
					"id" : "api_test::@10fae538ba4e8521554e",
					"jsonFile" : "target-api_test-RelWithDebInfo-b10b084477b090d99cc5.json",
					"name" : "api_test",
					"projectIndex" : 0
				},
				{
					"directoryIndex" : 1,
					"id" : "core::@57760688d1f824db5d9c",
					"jsonFile" : "target-core-RelWithDebInfo-37b8e3a48bc29a221ed2.json",
					"name" : "core",
					"projectIndex" : 0
				},
				{
					"directoryIndex" : 1,
					"id" : "core_test::@57760688d1f824db5d9c",
					"jsonFile" : "target-core_test-RelWithDebInfo-13b1c60509176e703d28.json",
					"name" : "core_test",
					"projectIndex" : 0
				},
				{
					"directoryIndex" : 0,
					"id" : "main::@6890427a1f51a3e7e1df",
					"jsonFile" : "target-main-RelWithDebInfo-bd5c25828f963fa93055.json",
					"name" : "main",
					"projectIndex" : 0
				},
				{
					"directoryIndex" : 2,
					"id" : "trigger_sample::@10fae538ba4e8521554e",
					"jsonFile" : "target-trigger_sample-RelWithDebInfo-02bc5146cc0b9520339d.json",
					"name" : "trigger_sample",
					"projectIndex" : 0
				}
			]
		}
	],
	"kind" : "codemodel",
	"paths" : 
	{
		"build" : "C:/Users/Mat/special_repo/game_motor_system/motor_game_system/cmake-build-relwithdebinfo",
		"source" : "C:/Users/Mat/special_repo/game_motor_system/motor_game_system"
	},
	"version" : 
	{
		"major" : 2,
		"minor" : 7
	}
}
